multiconn_archicad/__init__.py
multiconn_archicad/basic_types.py
multiconn_archicad/conn_header.py
multiconn_archicad/errors.py
multiconn_archicad/multi_conn.py
multiconn_archicad/py.typed
multiconn_archicad/standard_connection.py
multiconn_archicad/actions/__init__.py
multiconn_archicad/actions/connection_manager.py
multiconn_archicad/actions/project_handler.py
multiconn_archicad/actions/quit.py
multiconn_archicad/actions/refresh.py
multiconn_archicad/core/__init__.py
multiconn_archicad/core/core_commands.py
multiconn_archicad/core/literal_commands.py
multiconn_archicad/dialog_handlers/__init__.py
multiconn_archicad/dialog_handlers/dialog_handler_base.py
multiconn_archicad/dialog_handlers/win_dialog_handler.py
multiconn_archicad/dialog_handlers/win_int_handler_factory.py
multiconn_archicad/dicts/__init__.py
multiconn_archicad/dicts/extra_iems.py
multiconn_archicad/dicts/official/__init__.py
multiconn_archicad/dicts/official/commands.py
multiconn_archicad/dicts/official/types.py
multiconn_archicad/dicts/tapir/__init__.py
multiconn_archicad/dicts/tapir/commands.py
multiconn_archicad/dicts/tapir/types.py
multiconn_archicad/models/__init__.py
multiconn_archicad/models/base.py
multiconn_archicad/models/official/__init__.py
multiconn_archicad/models/official/commands.py
multiconn_archicad/models/official/types.py
multiconn_archicad/models/tapir/__init__.py
multiconn_archicad/models/tapir/commands.py
multiconn_archicad/models/tapir/types.py
multiconn_archicad/unified_api/__init__.py
multiconn_archicad/unified_api/api.py
multiconn_archicad/unified_api/official/__init__.py
multiconn_archicad/unified_api/official/addon.py
multiconn_archicad/unified_api/official/attribute.py
multiconn_archicad/unified_api/official/basic.py
multiconn_archicad/unified_api/official/classification.py
multiconn_archicad/unified_api/official/component.py
multiconn_archicad/unified_api/official/element_geometry.py
multiconn_archicad/unified_api/official/element_listing.py
multiconn_archicad-0.5.2.dist-info/METADATA
multiconn_archicad-0.5.2.dist-info/WHEEL
multiconn_archicad-0.5.2.dist-info/licenses/LICENSE
multiconn_archicad-0.5.2.dist-info/RECORD
