Metadata-Version: 2.4
Name: multiconn_archicad
Version: 0.5.2
Summary: A powerful Python toolkit for multi-instance Archicad automation, supporting the official JSON API and the Tapir Add-On.
Project-URL: Homepage, https://github.com/SzamosiMate/multiconn_archicad
Project-URL: Repository, https://github.com/SzamosiMate/multiconn_archicad
Project-URL: Bug Tracker, https://github.com/SzamosiMate/multiconn_archicad/issues
Author-email: SzamosiMate <szamimate@yahoo.com>
License: MIT License
License-File: LICENSE
Classifier: Development Status :: 4 - Beta
Classifier: Intended Audience :: Developers
Classifier: License :: OSI Approved :: MIT License
Classifier: Operating System :: OS Independent
Classifier: Programming Language :: Python
Classifier: Programming Language :: Python :: 3
Classifier: Programming Language :: Python :: 3.12
Classifier: Programming Language :: Python :: 3.13
Classifier: Programming Language :: Python :: 3.14
Classifier: Topic :: Software Development :: Libraries :: Python Modules
Requires-Python: <3.15,>=3.12
Requires-Dist: aiohttp<4.0,>=3.11.11
Requires-Dist: archicad>=28.3000
Requires-Dist: psutil<8.0,>=6.1.1
Requires-Dist: pydantic<3.0,>=2.11.7
Requires-Dist: typing-extensions>=4.12.2
Provides-Extra: dialog-handlers
Requires-Dist: pywinauto>=0.6.9; (platform_system == 'Windows') and extra == 'dialog-handlers'
